pathway_subtyping/__init__.py
pathway_subtyping/__main__.py
pathway_subtyping/cli.py
pathway_subtyping/config.py
pathway_subtyping/cross_cohort.py
pathway_subtyping/pipeline.py
pathway_subtyping/validation.py
pathway_subtyping/utils/__init__.py
pathway_subtyping/utils/performance.py
pathway_subtyping/utils/seed.py
pathway_subtyping-0.1.0.dist-info/licenses/LICENSE
pathway_subtyping-0.1.0.dist-info/METADATA
pathway_subtyping-0.1.0.dist-info/WHEEL
pathway_subtyping-0.1.0.dist-info/entry_points.txt
pathway_subtyping-0.1.0.dist-info/top_level.txt
pathway_subtyping-0.1.0.dist-info/RECORD
