Metadata-Version: 2.4
Name: pathway-subtyping
Version: 0.1.0
Summary: A disease-agnostic framework for identifying molecular subtypes through pathway-based analysis of rare genetic variants
Author-email: Rohit Chauhan <info@topmist.com>
Maintainer-email: Rohit Chauhan <info@topmist.com>
License: MIT
Project-URL: Homepage, https://github.com/topmist-admin/pathway-subtyping-framework
Project-URL: Documentation, https://github.com/topmist-admin/pathway-subtyping-framework#readme
Project-URL: Repository, https://github.com/topmist-admin/pathway-subtyping-framework.git
Project-URL: Issues, https://github.com/topmist-admin/pathway-subtyping-framework/issues
Project-URL: Changelog, https://github.com/topmist-admin/pathway-subtyping-framework/releases
Keywords: genomics,pathway-analysis,molecular-subtypes,clustering,rare-variants,bioinformatics,autism,neurogenetics
Classifier: Development Status :: 4 - Beta
Classifier: Intended Audience :: Science/Research
Classifier: Intended Audience :: Healthcare Industry
Classifier: License :: OSI Approved :: MIT License
Classifier: Operating System :: OS Independent
Classifier: Programming Language :: Python :: 3
Classifier: Programming Language :: Python :: 3.8
Classifier: Programming Language :: Python :: 3.9
Classifier: Programming Language :: Python :: 3.10
Classifier: Programming Language :: Python :: 3.11
Classifier: Programming Language :: Python :: 3.12
Classifier: Programming Language :: Python :: 3.13
Classifier: Topic :: Scientific/Engineering :: Bio-Informatics
Classifier: Topic :: Scientific/Engineering :: Medical Science Apps.
Requires-Python: >=3.8
License-File: LICENSE
Requires-Dist: numpy<2.0.0,>=1.24.0
Requires-Dist: pandas<3.0.0,>=2.0.0
Requires-Dist: scikit-learn<2.0.0,>=1.3.0
Requires-Dist: scipy<2.0.0,>=1.11.0
Requires-Dist: pysam<1.0.0,>=0.21.0
Requires-Dist: pyyaml<7.0,>=6.0
Requires-Dist: click<9.0.0,>=8.0.0
Requires-Dist: matplotlib<4.0.0,>=3.7.0
Requires-Dist: seaborn<1.0.0,>=0.12.0
Requires-Dist: jinja2<4.0.0,>=3.1.0
Requires-Dist: tqdm<5.0.0,>=4.65.0
Provides-Extra: dev
Requires-Dist: pytest>=7.0.0; extra == "dev"
Requires-Dist: pytest-cov>=4.0.0; extra == "dev"
Requires-Dist: black>=23.0.0; extra == "dev"
Requires-Dist: isort>=5.12.0; extra == "dev"
Requires-Dist: flake8>=6.0.0; extra == "dev"
Requires-Dist: mypy>=1.0.0; extra == "dev"
Requires-Dist: pre-commit>=3.0.0; extra == "dev"
Provides-Extra: notebooks
Requires-Dist: jupyter>=1.0.0; extra == "notebooks"
Requires-Dist: ipykernel>=6.0.0; extra == "notebooks"
Requires-Dist: nbformat>=5.0.0; extra == "notebooks"
Provides-Extra: docs
Requires-Dist: sphinx>=6.0.0; extra == "docs"
Requires-Dist: sphinx-rtd-theme>=1.2.0; extra == "docs"
Requires-Dist: myst-parser>=1.0.0; extra == "docs"
Provides-Extra: all
Requires-Dist: pathway-subtyping[dev,docs,notebooks]; extra == "all"
Dynamic: license-file
